pydebiaseddta/__init__.py
pydebiaseddta/data/dta/dta_sample_data.json
pydebiaseddta/data/dta/dta_sample_data.mini.json
pydebiaseddta/data/sequence/chembl27.mini.smiles
pydebiaseddta/data/word_identification/chemical_mini_test.json
pydebiaseddta/data/word_identification/chemical/chembl27_enc_94.json
pydebiaseddta/data/word_identification/chemical/chembl27_enc_bpe_8000.json
pydebiaseddta/data/word_identification/chemical/chembl27_encoding.json
pydebiaseddta/data/word_identification/protein/uniprot_26.json
pydebiaseddta/data/word_identification/protein/uniprot_bpe_32000.json
pydebiaseddta/debiasing/__init__.py
pydebiaseddta/debiasing/debiaseddta.py
pydebiaseddta/evaluation/__init__.py
pydebiaseddta/evaluation/evaluation.py
pydebiaseddta/guides/__init__.py
pydebiaseddta/guides/base_guide.py
pydebiaseddta/guides/bowdta.py
pydebiaseddta/guides/iddta.py
pydebiaseddta/predictors/__init__.py
pydebiaseddta/predictors/base_predictors.py
pydebiaseddta/predictors/bpedta.py
pydebiaseddta/predictors/deepdta.py
pydebiaseddta/predictors/lmdta.py
pydebiaseddta/sequence/__init__.py
pydebiaseddta/sequence/smiles_processing.py
pydebiaseddta/sequence/word_identification.py
pydebiaseddta/utils/__init__.py
pydebiaseddta/utils/utils.py
testpydebiaseddta-0.0.3.dist-info/LICENSE
testpydebiaseddta-0.0.3.dist-info/METADATA
testpydebiaseddta-0.0.3.dist-info/WHEEL
testpydebiaseddta-0.0.3.dist-info/top_level.txt
testpydebiaseddta-0.0.3.dist-info/RECORD
